[
null,
{"id":1,"members":[{"enemyId":3,"x":408,"y":436,"hidden":false}],"name":"","pages":[{"conditions":{"actorHp":50,"actorId":1,"actorValid":false,"enemyHp":50,"enemyIndex":0,"enemyValid":false,"switchId":1,"switchValid":false,"turnA":0,"turnB":0,"turnEnding":false,"turnValid":false},"list":[{"code":0,"indent":0,"parameters":[]}],"span":0}]},
{"id":2,"members":[],"name":"","pages":[{"conditions":{"actorHp":50,"actorId":1,"actorValid":false,"enemyHp":50,"enemyIndex":0,"enemyValid":false,"switchId":1,"switchValid":false,"turnA":0,"turnB":0,"turnEnding":false,"turnValid":false},"list":[{"code":0,"indent":0,"parameters":[]}],"span":0}]},
{"id":3,"members":[{"enemyId":3,"x":408,"y":436,"hidden":false}],"name":"BUTO IJO","pages":[{"conditions":{"actorHp":50,"actorId":1,"actorValid":false,"enemyHp":50,"enemyIndex":0,"enemyValid":false,"switchId":1,"switchValid":false,"turnA":0,"turnB":0,"turnEnding":false,"turnValid":false},"list":[{"code":101,"indent":0,"parameters":["Monster",2,0,2]},{"code":401,"indent":0,"parameters":["HAHA AKU BUTO IJO AKU AKAN MEMBUNUH MU"]},{"code":101,"indent":0,"parameters":["anakmudah1 mulut buka",0,0,2]},{"code":401,"indent":0,"parameters":["TIDAK MUNGKIN AKU SUDAH MEMILIKI SENJATA"]},{"code":401,"indent":0,"parameters":["DARI PAK BLANGKON"]},{"code":0,"indent":0,"parameters":[]}],"span":0}]},
{"id":4,"members":[],"name":"","pages":[{"conditions":{"actorHp":50,"actorId":1,"actorValid":false,"enemyHp":50,"enemyIndex":0,"enemyValid":false,"switchId":1,"switchValid":false,"turnA":0,"turnB":0,"turnEnding":false,"turnValid":false},"list":[{"code":0,"indent":0,"parameters":[]}],"span":0}]}
]